interactor/__init__.py
interactor/__version__.py
interactor/interactor.py
interactor/session.py
ai_interactor-0.1.2.5.dist-info/METADATA
ai_interactor-0.1.2.5.dist-info/WHEEL
ai_interactor-0.1.2.5.dist-info/top_level.txt
ai_interactor-0.1.2.5.dist-info/RECORD
