Metadata-Version: 2.4
Name: ai-interactor
Version: 0.1.2.5
Summary: Universal AI interaction library with session and tool support.
Author-email: Wadih Khairallah <woodyk@gmail.com>
License: MIT
Project-URL: Homepage, https://github.com/woodyk/interactor
Keywords: text,extraction,pii,analysis
Classifier: Programming Language :: Python :: 3
Classifier: License :: OSI Approved :: MIT License
Classifier: Operating System :: OS Independent
Requires-Python: >=3.8
Requires-Dist: aiohttp
Requires-Dist: openai
Requires-Dist: rich
Requires-Dist: tiktoken
Requires-Dist: anthropic
Requires-Dist: requests
